setup.py
subredis.py
subredis.egg-info/PKG-INFO
subredis.egg-info/SOURCES.txt
subredis.egg-info/dependency_links.txt
subredis.egg-info/requires.txt
subredis.egg-info/top_level.txt