Metadata-Version: 1.1
Name: subredis
Version: 0.0.5
Summary: A Redis within your Redis
Home-page: UNKNOWN
Author: Doug Turnbull
Author-email: softwaredoug@gmail.com
License: Apache
Keywords: redis,database
Platform: UNKNOWN
Classifier: Programming Language :: Python
Classifier: Programming Language :: Python :: 3
Classifier: Intended Audience :: Developers
Classifier: License :: OSI Approved :: Apache Software License
Classifier: Topic :: Database
Classifier: Development Status :: 4 - Beta
